odoo/addons/membership_prorate_variable_period/README.rst
odoo/addons/membership_prorate_variable_period/__init__.py
odoo/addons/membership_prorate_variable_period/__manifest__.py
odoo/addons/membership_prorate_variable_period/i18n/ar.po
odoo/addons/membership_prorate_variable_period/i18n/bs.po
odoo/addons/membership_prorate_variable_period/i18n/ca.po
odoo/addons/membership_prorate_variable_period/i18n/cs.po
odoo/addons/membership_prorate_variable_period/i18n/de.po
odoo/addons/membership_prorate_variable_period/i18n/en_GB.po
odoo/addons/membership_prorate_variable_period/i18n/es.po
odoo/addons/membership_prorate_variable_period/i18n/es_CR.po
odoo/addons/membership_prorate_variable_period/i18n/es_EC.po
odoo/addons/membership_prorate_variable_period/i18n/es_MX.po
odoo/addons/membership_prorate_variable_period/i18n/et.po
odoo/addons/membership_prorate_variable_period/i18n/fi.po
odoo/addons/membership_prorate_variable_period/i18n/fr.po
odoo/addons/membership_prorate_variable_period/i18n/fr_CH.po
odoo/addons/membership_prorate_variable_period/i18n/hr.po
odoo/addons/membership_prorate_variable_period/i18n/hr_HR.po
odoo/addons/membership_prorate_variable_period/i18n/hu.po
odoo/addons/membership_prorate_variable_period/i18n/it.po
odoo/addons/membership_prorate_variable_period/i18n/ja.po
odoo/addons/membership_prorate_variable_period/i18n/lt.po
odoo/addons/membership_prorate_variable_period/i18n/membership_prorate_variable_period.pot
odoo/addons/membership_prorate_variable_period/i18n/mk.po
odoo/addons/membership_prorate_variable_period/i18n/mn.po
odoo/addons/membership_prorate_variable_period/i18n/nb.po
odoo/addons/membership_prorate_variable_period/i18n/nl.po
odoo/addons/membership_prorate_variable_period/i18n/nl_BE.po
odoo/addons/membership_prorate_variable_period/i18n/nl_NL.po
odoo/addons/membership_prorate_variable_period/i18n/pt.po
odoo/addons/membership_prorate_variable_period/i18n/pt_BR.po
odoo/addons/membership_prorate_variable_period/i18n/pt_PT.po
odoo12_addon_membership_prorate_variable_period-12.0.1.0.0.99.dev8.dist-info/METADATA
odoo12_addon_membership_prorate_variable_period-12.0.1.0.0.99.dev8.dist-info/WHEEL
odoo12_addon_membership_prorate_variable_period-12.0.1.0.0.99.dev8.dist-info/top_level.txt
odoo12_addon_membership_prorate_variable_period-12.0.1.0.0.99.dev8.dist-info/RECORD
